pytracking/__init__.py
pytracking/django.py
pytracking/html.py
pytracking/tracking.py
pytracking/webhook.py
pytracking-0.2.2.dist-info/AUTHORS.txt
pytracking-0.2.2.dist-info/LICENSE
pytracking-0.2.2.dist-info/METADATA
pytracking-0.2.2.dist-info/WHEEL
pytracking-0.2.2.dist-info/top_level.txt
pytracking-0.2.2.dist-info/RECORD
