Metadata-Version: 2.1
Name: pytracking
Version: 0.2.2
Summary: Email open and click tracking
Home-page: https://github.com/resulto-admin/pytracking
Author: Resulto Dev Team
Author-email: dev@resulto.ca
License: New BSD
Keywords: email open click tracking
Platform: UNKNOWN
Classifier: Development Status :: 5 - Production/Stable
Classifier: Intended Audience :: Developers
Classifier: Topic :: Communications :: Email
Classifier: Topic :: Software Development :: Libraries :: Python Modules
Classifier: License :: OSI Approved :: BSD License
Classifier: Programming Language :: Python :: 3
Classifier: Programming Language :: Python :: 3.6
Classifier: Programming Language :: Python :: 3.7
Classifier: Programming Language :: Python :: 3.8
Classifier: Programming Language :: Python :: 3.9
Provides-Extra: all
Requires-Dist: tox (>=2.3.1) ; extra == 'all'
Requires-Dist: pytest (>=2.9.2) ; extra == 'all'
Requires-Dist: requests (>=2.10.0) ; extra == 'all'
Requires-Dist: lxml (>=3.6.1) ; extra == 'all'
Requires-Dist: cryptography (>=1.4) ; extra == 'all'
Requires-Dist: django-ipware (>=2.0.0) ; extra == 'all'
Requires-Dist: django (>=1.11) ; extra == 'all'
Provides-Extra: crypto
Requires-Dist: cryptography (>=1.4) ; extra == 'crypto'
Provides-Extra: django
Requires-Dist: django-ipware (>=2.0.0) ; extra == 'django'
Requires-Dist: django (>=1.11) ; extra == 'django'
Provides-Extra: html
Requires-Dist: lxml (>=3.6.1) ; extra == 'html'
Provides-Extra: test
Requires-Dist: tox (>=2.3.1) ; extra == 'test'
Requires-Dist: pytest (>=2.9.2) ; extra == 'test'
Provides-Extra: webhook
Requires-Dist: requests (>=2.10.0) ; extra == 'webhook'
